README.md
setup.cfg
setup.py
mkpyros.egg-info/PKG-INFO
mkpyros.egg-info/SOURCES.txt
mkpyros.egg-info/dependency_links.txt
mkpyros.egg-info/requires.txt
mkpyros.egg-info/top_level.txt
pyros/__init__.py
pyros/main.py
pyros/core/__init__.py
pyros/core/baseline.py
pyros/core/engine.py
pyros/core/evaluation.py
pyros/core/recommender.py
pyros/data/__init__.py
pyros/data/dataset.py
pyros/data/mapping.py
pyros/data/reader.py
pyros/utils/__init__.py
pyros/utils/binarizer.py
pyros/utils/bool_kernels.py
pyros/utils/cvx.py
pyros/utils/kernels.py
pyros/utils/misc.py
pyros/utils/num.py
pyros/utils/prop_kernels.py
pyros/utils/scaled_bk.py