Metadata-Version: 1.1
Name: mkpyros
Version: 0.9.29
Summary: Python module for building and evaluating recommender systems for implicit feedback. Full documentation @ http://mkpyros.readthedocs.io/en/latest/
Home-page: https://github.com/makgyver/pyros
Author: Mirko Polato
Author-email: mak1788@gmail.com
License: MIT
Download-URL: https://github.com/makgyver/pyros
Keywords: recommendation-algorithm,collaborative-filtering,algorithm,kernel
Platform: UNKNOWN
Classifier: Development Status :: 3 - Alpha
Classifier: Programming Language :: Python :: 2.7
Classifier: Topic :: Scientific/Engineering :: Artificial Intelligence
Classifier: License :: OSI Approved :: MIT License
